pricehub/__init__.py
pricehub/config.py
pricehub/get_ohlc_impl.py
pricehub/brokers/__init__.py
pricehub/brokers/broker_abc.py
pricehub/brokers/broker_binance_abc.py
pricehub/brokers/broker_binance_futures.py
pricehub/brokers/broker_binance_spot.py
pricehub/brokers/broker_bybit_abc.py
pricehub/brokers/broker_bybit_inverse.py
pricehub/brokers/broker_bybit_linear.py
pricehub/brokers/broker_bybit_spot.py
pricehub/brokers/broker_coinbase_spot.py
pricehub/brokers/broker_kraken_spot.py
pricehub/brokers/broker_kucoin_futures.py
pricehub/brokers/broker_kucoin_spot.py
pricehub/brokers/broker_okx_futures.py
pricehub/brokers/broker_okx_spot.py
pricehub/models/__init__.py
pricehub/models/broker.py
pricehub/models/get_ohlc_params.py
pricehub/models/types_common.py
pricehub-0.0.7.dist-info/licenses/LICENSE
pricehub-0.0.7.dist-info/METADATA
pricehub-0.0.7.dist-info/WHEEL
pricehub-0.0.7.dist-info/top_level.txt
pricehub-0.0.7.dist-info/RECORD
