Metadata-Version: 2.4
Name: pricehub
Version: 0.0.7
Summary: Pricehub: Unified Python Package for Collecting OHLC Prices from Binance, Bybit, and Coinbase APIs into a DataFrame
Home-page: https://github.com/eslazarev/pricehub
Author: Evgenii Lazarev
Author-email: elazarev@gmail.com
Project-URL: GitHub, https://github.com/eslazarev
Project-URL: LinkedIn, https://www.linkedin.com/in/elazarev
Keywords: OHLC OHLCV prices binance bybit coinbase trading  finance quant algotrading cryptocurrency crypto futures spot broker exchange market quantitative historical candlestick back-testing dataframe
Classifier: Programming Language :: Python
Classifier: Programming Language :: Python :: 3
Classifier: Programming Language :: Python :: 3 :: Only
Classifier: Programming Language :: Python :: 3.8
Classifier: Programming Language :: Python :: 3.9
Classifier: Programming Language :: Python :: 3.10
Classifier: Programming Language :: Python :: 3.11
Classifier: Programming Language :: Python :: 3.12
Classifier: Programming Language :: Python :: 3.13
Classifier: License :: OSI Approved :: MIT License
Classifier: Operating System :: OS Independent
Classifier: Intended Audience :: Developers
Classifier: Intended Audience :: Education
Classifier: Intended Audience :: Financial and Insurance Industry
Classifier: Intended Audience :: Information Technology
Classifier: Development Status :: 3 - Alpha
Classifier: Topic :: Office/Business
Classifier: Topic :: Office/Business
Classifier: Topic :: Office/Business :: Financial
Classifier: Topic :: Office/Business :: Financial :: Investment
Classifier: Natural Language :: English
Requires-Python: >=3.8
License-File: LICENSE
Requires-Dist: pandas
Requires-Dist: pydantic>=2.0.1
Requires-Dist: arrow>=1.0.0
Requires-Dist: requests
Dynamic: author
Dynamic: author-email
Dynamic: classifier
Dynamic: description
Dynamic: description-content-type
Dynamic: home-page
Dynamic: keywords
Dynamic: license-file
Dynamic: project-url
Dynamic: requires-dist
Dynamic: requires-python
Dynamic: summary
